burgos/__init__.py
burgos/mysql_handler.py
burgos/prettyPrint.py
burgos/reqcheq.py
burgos/session.py
burgos/togglePrint.py
burgos-2.2.1.dist-info/METADATA
burgos-2.2.1.dist-info/WHEEL
burgos-2.2.1.dist-info/licenses/LICENSE
burgos-2.2.1.dist-info/RECORD
