Metadata-Version: 2.1
Name: burgos
Version: 2.2.1
Summary: A bundle of useful packages for managing login sessions and database
Project-URL: Homepage, https://github.com/nandobfer/burgos
Project-URL: Bug Tracker, https://github.com/nandobfer/burgos/issues
Author-email: Fernando Burgos <nandobfer@gmail.com>
License:                       GNU GENERAL PUBLIC LICENSE
License-File: LICENSE
Classifier: License :: OSI Approved :: MIT License
Classifier: Operating System :: OS Independent
Classifier: Programming Language :: Python :: 3
Requires-Python: >=3.6
Requires-Dist: mysql-connector-python==8.0.30
